econcycle/__init__.py
econcycle/utils/__init__.py
econcycle/utils/chart/__init__.py
econcycle/utils/cycle/__init__.py
econcycle-0.0.8.dist-info/LICENSE
econcycle-0.0.8.dist-info/METADATA
econcycle-0.0.8.dist-info/WHEEL
econcycle-0.0.8.dist-info/top_level.txt
econcycle-0.0.8.dist-info/RECORD
