Metadata-Version: 2.1
Name: econcycle
Version: 0.0.8
Summary: Get Calculated Economic Cycle
Home-page: https://github.com/skwon2345/econcycle
Author: Sukkwon On
Author-email: skwon2345@gmail.com
Project-URL: Bug Tracker, https://github.com/skwon2345/econcycle/issues
Classifier: Programming Language :: Python :: 3
Classifier: License :: OSI Approved :: MIT License
Classifier: Operating System :: OS Independent
Requires-Python: >=3.9
License-File: LICENSE
Requires-Dist: finnhub-python (==2.4.15)
